pychasing/__init__.py
pychasing/client.py
pychasing/enums.py
pychasing/models.py
pychasing-0.1.8.dist-info/LICENSE
pychasing-0.1.8.dist-info/METADATA
pychasing-0.1.8.dist-info/WHEEL
pychasing-0.1.8.dist-info/top_level.txt
pychasing-0.1.8.dist-info/RECORD
