Metadata-Version: 2.1
Name: pychasing
Version: 0.1.8
Summary: Short description
Author-email: "Tanner B. Corcoran" <tannerbcorcoran@gmail.com>
License: MIT License
Project-URL: repository, https://github.com/tanrbobanr/pychasing
Project-URL: documentation, https://github.com/tanrbobanr/pychasing/blob/main/README.md
Project-URL: changelog, https://github.com/tanrbobanr/pychasing/blob/main/changelog.md
Keywords: a,b,c
Classifier: Development Status :: 5 - Production/Stable
Classifier: Intended Audience :: Developers
Classifier: License :: OSI Approved :: MIT License
Classifier: Operating System :: OS Independent
Classifier: Programming Language :: Python :: 3
Classifier: Programming Language :: Python :: 3.7
Classifier: Programming Language :: Python :: 3.8
Classifier: Programming Language :: Python :: 3.9
Classifier: Programming Language :: Python :: 3.10
Classifier: Programming Language :: Python :: 3.11
Classifier: Programming Language :: Python :: 3.12
Classifier: Topic :: Software Development
Classifier: Topic :: Software Development :: Libraries
Classifier: Topic :: Software Development :: Libraries :: Python Modules
Classifier: Topic :: Utilities
Classifier: Typing :: Typed
Requires-Python: >=3.7
License-File: LICENSE
Requires-Dist: requests (>=2.27.1)
Requires-Dist: http-prep (>=0.0.6)
Requires-Dist: rlim (>=0.0.2)
